hass_apps/__init__.py
hass_apps/common.py
hass_apps/loader.py
hass_apps/schedy/__init__.py
hass_apps/schedy/app.py
hass_apps/schedy/config.py
hass_apps/schedy/room.py
hass_apps/schedy/schedule.py
hass_apps/schedy/stats.py
hass_apps/schedy/util.py
hass_apps/schedy/actor/__init__.py
hass_apps/schedy/actor/base.py
hass_apps/schedy/actor/custom.py
hass_apps/schedy/actor/generic.py
hass_apps/schedy/actor/generic2.py
hass_apps/schedy/actor/switch.py
hass_apps/schedy/actor/thermostat.py
hass_apps/schedy/expression/__init__.py
hass_apps/schedy/expression/helpers.py
hass_apps/schedy/expression/types.py
hass_apps-0.20200319.0.dist-info/LICENSE
hass_apps-0.20200319.0.dist-info/METADATA
hass_apps-0.20200319.0.dist-info/WHEEL
hass_apps-0.20200319.0.dist-info/top_level.txt
hass_apps-0.20200319.0.dist-info/RECORD
