Metadata-Version: 2.1
Name: hass-apps
Version: 0.20200319.0
Summary: A collection of useful apps for AppDaemon + Home Assistant.
Home-page: https://github.com/efficiosoft/hass-apps
Author: Robert Schindler
Author-email: r.schindler@efficiosoft.com
License: Apache 2.0
Platform: UNKNOWN
Requires-Dist: appdaemon (<5,>=3.0)
Requires-Dist: cached-property (~=1.5)
Requires-Dist: observable (~=1.0)
Requires-Dist: voluptuous (~=0.11)
